{
  "id": "preset_level_1",
  "name": "初出茅庐",
  "description": "熟悉游戏操作，达到目标分数即可通关",
  "levelNumber": 1,
  "isUnlocked": true,
  "isCustom": false,
  "victoryCondition": {
    "type": 0,
    "targetScore": 100,
    "targetLength": 10,
    "mustCollectAllFood": false,
    "foodSpawnCount": null
  },
  "obstacles": [],
  "settings": {
    "defaultDifficulty": 0,
    "initialSpeedLevel": 3,
    "gridWidth": 30,
    "gridHeight": 20,
    "snakeStartPosition": { "x": 15, "y": 10 },
    "initialDirection": { "x": 1, "y": 0 },
    "initialSnakeLength": 3,
    "foodCount": 1,
    "enableDynamicObstacles": false
  }
}

/* 测试配置（方便调试时使用）:
{
  "victoryCondition": {
    "targetScore": 10,           // 改为10分，吃1个食物就胜利
    "foodSpawnCount": 1          // 只生成1个食物
  },
  "settings": {
    "snakeStartPosition": { "x": 5, "y": 10 },
    "foodCount": 0               // 设为0，使用固定食物位置
  },
  "fixedFoodPositions": [        // 固定食物在蛇前方
    { "x": 6, "y": 10 }
  ]
}
*/
